Metadata-Version: 1.0
Name: mfb-kiban-dependence-egg
Version: 0.1.0
Summary: test how to make eggs
Home-page: UNKNOWN
Author: taoxl
Author-email: 379575221@qq.com
License: 1
Keywords: mfb_kiban_dependence,python
Platform: Independant
